cronner/__init__.py
cronner/cronner.py
cronner/kronjob_util.py
cronner-0.7.6.dist-info/LICENSE.txt
cronner-0.7.6.dist-info/METADATA
cronner-0.7.6.dist-info/WHEEL
cronner-0.7.6.dist-info/top_level.txt
cronner-0.7.6.dist-info/RECORD
