Metadata-Version: 2.1
Name: cronner
Version: 0.7.6
Summary: Easily schedule python functions to be run under the cron daemon.
Home-page: https://github.com/better/cronner
Author: Liam Buchanan
Author-email: liam@better.com
License: MIT
Keywords: cron crontab
Platform: UNKNOWN
Provides-Extra: kronner
Requires-Dist: pyyaml ; extra == 'kronner'
